FlaskZhilv/README.md
FlaskZhilv/__init__.py
FlaskZhilv/__main__.py
FlaskZhilv/file.epub
FlaskZhilv/index.html
FlaskZhilv/css/__init__.py
FlaskZhilv/css/annotations.css
FlaskZhilv/css/main.css
FlaskZhilv/css/normalize.css
FlaskZhilv/css/popup.css
FlaskZhilv/font/__init__.py
FlaskZhilv/font/fontello.eot
FlaskZhilv/font/fontello.svg
FlaskZhilv/font/fontello.ttf
FlaskZhilv/font/fontello.woff
FlaskZhilv/img/__init__.py
FlaskZhilv/img/annotator-glyph-sprite.png
FlaskZhilv/img/annotator-icon-sprite.png
FlaskZhilv/img/apple-touch-icon.png
FlaskZhilv/img/cancelfullscreen.png
FlaskZhilv/img/close.png
FlaskZhilv/img/fullscreen.png
FlaskZhilv/img/loader.gif
FlaskZhilv/img/menu-icon.png
FlaskZhilv/img/save.png
FlaskZhilv/img/saved.png
FlaskZhilv/img/settings-s.png
FlaskZhilv/img/settings.png
FlaskZhilv/img/star.png
FlaskZhilv/js/__init__.py
FlaskZhilv/js/epub.js
FlaskZhilv/js/epub.min.js
FlaskZhilv/js/epub.min.map
FlaskZhilv/js/hooks.min.js
FlaskZhilv/js/hooks.min.map
FlaskZhilv/js/reader.js
FlaskZhilv/js/reader.js.map
FlaskZhilv/js/reader.min.js
FlaskZhilv/js/reader.min.map
FlaskZhilv/js/hooks/__init__.py
FlaskZhilv/js/hooks/extensions/__init__.py
FlaskZhilv/js/hooks/extensions/highlight.js
FlaskZhilv/js/libs/__init__.py
FlaskZhilv/js/libs/jquery.min.js
FlaskZhilv/js/libs/localforage.min.js
FlaskZhilv/js/libs/screenfull.js
FlaskZhilv/js/libs/screenfull.min.js
FlaskZhilv/js/libs/zip.min.js
FlaskZhilv/js/plugins/__init__.py
FlaskZhilv/js/plugins/hypothesis.js
FlaskZhilv/js/plugins/search.js
flask_zhilv-2024.3.2.0.dist-info/METADATA
flask_zhilv-2024.3.2.0.dist-info/WHEEL
flask_zhilv-2024.3.2.0.dist-info/entry_points.txt
flask_zhilv-2024.3.2.0.dist-info/top_level.txt
flask_zhilv-2024.3.2.0.dist-info/RECORD
